[{"code":"1010","theta":"","conductivity":""},
{"code":"1011","theta":"","conductivity":""},
{"code":"1012","theta":"","conductivity":""},
{"code":"1013","theta":"","conductivity":""},
{"code":"1014","theta":"","conductivity":""},
{"code":"1015","theta":"","conductivity":""},
{"code":"1020","theta":"","conductivity":""},
{"code":"1021","theta":"","conductivity":""},
{"code":"1022","theta":"","conductivity":""},
{"code":"1023","theta":"","conductivity":""},
{"code":"1024","theta":"","conductivity":""},
{"code":"1030","theta":"","conductivity":""},
{"code":"1031","theta":"","conductivity":""},
{"code":"1032","theta":"","conductivity":""},
{"code":"1040","theta":"","conductivity":""},
{"code":"1041","theta":"","conductivity":""},
{"code":"1042","theta":"","conductivity":""},
{"code":"1043","theta":"","conductivity":""},
{"code":"1050","theta":"","conductivity":""},
{"code":"1051","theta":"","conductivity":""},
{"code":"1052","theta":"","conductivity":""},
{"code":"1053","theta":"","conductivity":""},
{"code":"1054","theta":"","conductivity":""},
{"code":"1060","theta":"","conductivity":""},
{"code":"1061","theta":"","conductivity":""},
{"code":"1062","theta":"","conductivity":""},
{"code":"1063","theta":"","conductivity":""},
{"code":"1070","theta":"","conductivity":""},
{"code":"1071","theta":"","conductivity":""},
{"code":"1072","theta":"","conductivity":""},
{"code":"1073","theta":"","conductivity":""},
{"code":"1074","theta":"","conductivity":""},
{"code":"1075","theta":"","conductivity":""},
{"code":"1080","theta":"","conductivity":""},
{"code":"1081","theta":"","conductivity":""},
{"code":"1082","theta":"","conductivity":""},
{"code":"1083","theta":"","conductivity":""},
{"code":"1084","theta":"","conductivity":""},
{"code":"1085","theta":"","conductivity":""},
{"code":"1086","theta":"","conductivity":""},
{"code":"1087","theta":"","conductivity":""},
{"code":"1090","theta":"","conductivity":""},
{"code":"1091","theta":"","conductivity":""},
{"code":"1092","theta":"","conductivity":""},
{"code":"1100","theta":"","conductivity":""},
{"code":"1101","theta":"","conductivity":""},
{"code":"1102","theta":"","conductivity":""},
{"code":"1103","theta":"","conductivity":""},
{"code":"1104","theta":"","conductivity":""},
{"code":"1110","theta":"","conductivity":""},
{"code":"1111","theta":"","conductivity":""},
{"code":"1112","theta":"","conductivity":""},
{"code":"1113","theta":"","conductivity":""},
{"code":"1114","theta":"","conductivity":""},
{"code":"1115","theta":"","conductivity":""},
{"code":"1116","theta":"","conductivity":""},
{"code":"1117","theta":"","conductivity":""},
{"code":"1120","theta":"","conductivity":""},
{"code":"1121","theta":"","conductivity":""},
{"code":"1122","theta":"","conductivity":""},
{"code":"1123","theta":"","conductivity":""},
{"code":"1130","theta":"","conductivity":""},
{"code":"1131","theta":"","conductivity":""},
{"code":"1132","theta":"","conductivity":""},
{"code":"1133","theta":"","conductivity":""},
{"code":"1134","theta":"","conductivity":""},
{"code":"1135","theta":"","conductivity":""},
{"code":"1140","theta":"","conductivity":""},
{"code":"1141","theta":"","conductivity":""},
{"code":"1142","theta":"","conductivity":""},
{"code":"1143","theta":"","conductivity":""},
{"code":"1150","theta":"","conductivity":""},
{"code":"1151","theta":"","conductivity":""},
{"code":"1152","theta":"","conductivity":""},
{"code":"1160","theta":"","conductivity":""},
{"code":"1161","theta":"","conductivity":""},
{"code":"1162","theta":"","conductivity":""},
{"code":"1163","theta":"","conductivity":""},
{"code":"1164","theta":"","conductivity":""},
{"code":"1165","theta":"","conductivity":""},
{"code":"1166","theta":"","conductivity":""},
{"code":"1170","theta":"","conductivity":""},
{"code":"1171","theta":"","conductivity":""},
{"code":"1172","theta":"","conductivity":""},
{"code":"1173","theta":"","conductivity":""},
{"code":"1174","theta":"","conductivity":""},
{"code":"1180","theta":"","conductivity":""},
{"code":"1181","theta":"","conductivity":""},
{"code":"1182","theta":"","conductivity":""},
{"code":"1183","theta":"","conductivity":""},
{"code":"1184","theta":"","conductivity":""},
{"code":"1190","theta":"","conductivity":""},
{"code":"1191","theta":"","conductivity":""},
{"code":"1192","theta":"","conductivity":""},
{"code":"1193","theta":"","conductivity":""},
{"code":"1194","theta":"","conductivity":""},
{"code":"1200","theta":"","conductivity":""},
{"code":"1201","theta":"","conductivity":""},
{"code":"1202","theta":"","conductivity":""},
{"code":"1203","theta":"","conductivity":""},
{"code":"1204","theta":"","conductivity":""},
{"code":"1210","theta":"","conductivity":""},
{"code":"1211","theta":"","conductivity":""},
{"code":"1212","theta":"","conductivity":""},
{"code":"1213","theta":"","conductivity":""},
{"code":"1220","theta":"","conductivity":""},
{"code":"1221","theta":"","conductivity":""},
{"code":"1222","theta":"","conductivity":""},
{"code":"1223","theta":"","conductivity":""},
{"code":"1224","theta":"","conductivity":""},
{"code":"1225","theta":"","conductivity":""},
{"code":"1230","theta":"","conductivity":""},
{"code":"1231","theta":"","conductivity":""},
{"code":"1232","theta":"","conductivity":""},
{"code":"1233","theta":"","conductivity":""},
{"code":"1234","theta":"","conductivity":""},
{"code":"1235","theta":"","conductivity":""},
{"code":"1236","theta":"","conductivity":""},
{"code":"1237","theta":"","conductivity":""},
{"code":"1240","theta":"","conductivity":""},
{"code":"1241","theta":"","conductivity":""},
{"code":"1260","theta":"","conductivity":""},
{"code":"1261","theta":"","conductivity":""},
{"code":"1270","theta":"","conductivity":""},
{"code":"1280","theta":"","conductivity":""},
{"code":"1281","theta":"","conductivity":""},
{"code":"1282","theta":"","conductivity":""},
{"code":"1290","theta":"","conductivity":""},
{"code":"1300","theta":"","conductivity":""},
{"code":"1301","theta":"","conductivity":""},
{"code":"1310","theta":"","conductivity":""},
{"code":"1320","theta":"","conductivity":""},
{"code":"1330","theta":"","conductivity":""},
{"code":"1331","theta":"","conductivity":""},
{"code":"1340","theta":"","conductivity":""},
{"code":"1341","theta":"","conductivity":""},
{"code":"1342","theta":"","conductivity":""},
{"code":"1350","theta":"","conductivity":""},
{"code":"1351","theta":"","conductivity":""},
{"code":"1352","theta":"","conductivity":""},
{"code":"1360","theta":"","conductivity":""},
{"code":"1361","theta":"","conductivity":""},
{"code":"1362","theta":"","conductivity":""},
{"code":"1370","theta":"","conductivity":""},
{"code":"1371","theta":"","conductivity":""},
{"code":"1372","theta":"","conductivity":""},
{"code":"1380","theta":"","conductivity":""},
{"code":"1381","theta":"","conductivity":""},
{"code":"1382","theta":"","conductivity":""},
{"code":"1383","theta":"","conductivity":""},
{"code":"1390","theta":"","conductivity":""},
{"code":"1391","theta":"","conductivity":""},
{"code":"1392","theta":"","conductivity":""},
{"code":"1400","theta":"","conductivity":""},
{"code":"1410","theta":"","conductivity":""},
{"code":"1420","theta":"","conductivity":""},
{"code":"1430","theta":"","conductivity":""},
{"code":"1440","theta":"","conductivity":""},
{"code":"1450","theta":"","conductivity":""},
{"code":"1460","theta":"","conductivity":""},
{"code":"1461","theta":"","conductivity":""},
{"code":"1462","theta":"","conductivity":""},
{"code":"1463","theta":"","conductivity":""},
{"code":"1464","theta":"","conductivity":""},
{"code":"1465","theta":"","conductivity":""},
{"code":"1466","theta":"","conductivity":""},
{"code":"1467","theta":"","conductivity":""},
{"code":"1480","theta":"","conductivity":""},
{"code":"1481","theta":"","conductivity":""},
{"code":"1482","theta":"","conductivity":""},
{"code":"1490","theta":"","conductivity":""},
{"code":"2000","theta":"","conductivity":""},
{"code":"2001","theta":"","conductivity":""},
{"code":"2002","theta":"","conductivity":""},
{"code":"2010","theta":"","conductivity":""},
{"code":"2011","theta":"","conductivity":""},
{"code":"2012","theta":"","conductivity":""},
{"code":"2020","theta":"","conductivity":""},
{"code":"2021","theta":"","conductivity":""},
{"code":"2022","theta":"","conductivity":""},
{"code":"2030","theta":"","conductivity":""},
{"code":"2031","theta":"","conductivity":""},
{"code":"2032","theta":"","conductivity":""},
{"code":"2040","theta":"","conductivity":""},
{"code":"2041","theta":"","conductivity":""},
{"code":"2050","theta":"","conductivity":""},
{"code":"2051","theta":"","conductivity":""},
{"code":"2060","theta":"","conductivity":""},
{"code":"2061","theta":"","conductivity":""},
{"code":"2070","theta":"","conductivity":""},
{"code":"2071","theta":"","conductivity":""},
{"code":"2080","theta":"","conductivity":""},
{"code":"2081","theta":"","conductivity":""},
{"code":"2090","theta":"","conductivity":""},
{"code":"2091","theta":"","conductivity":""},
{"code":"2092","theta":"","conductivity":""},
{"code":"2100","theta":"","conductivity":""},
{"code":"2101","theta":"","conductivity":""},
{"code":"2102","theta":"","conductivity":""},
{"code":"2103","theta":"","conductivity":""},
{"code":"2104","theta":"","conductivity":""},
{"code":"2105","theta":"","conductivity":""},
{"code":"2110","theta":"","conductivity":""},
{"code":"2111","theta":"","conductivity":""},
{"code":"2120","theta":"","conductivity":""},
{"code":"2121","theta":"","conductivity":""},
{"code":"2122","theta":"","conductivity":""},
{"code":"2123","theta":"","conductivity":""},
{"code":"2124","theta":"","conductivity":""},
{"code":"2125","theta":"","conductivity":""},
{"code":"2126","theta":"","conductivity":""},
{"code":"2130","theta":"","conductivity":""},
{"code":"2131","theta":"","conductivity":""},
{"code":"2132","theta":"","conductivity":""},
{"code":"2140","theta":"","conductivity":""},
{"code":"2141","theta":"","conductivity":""},
{"code":"2150","theta":"","conductivity":""},
{"code":"2151","theta":"","conductivity":""},
{"code":"2160","theta":"","conductivity":""},
{"code":"2161","theta":"","conductivity":""},
{"code":"2170","theta":"","conductivity":""},
{"code":"2171","theta":"","conductivity":""},
{"code":"2180","theta":"","conductivity":""},
{"code":"2181","theta":"","conductivity":""},
{"code":"2190","theta":"","conductivity":""},
{"code":"2191","theta":"","conductivity":""},
{"code":"2192","theta":"","conductivity":""},
{"code":"2193","theta":"","conductivity":""},
{"code":"2194","theta":"","conductivity":""},
{"code":"2195","theta":"","conductivity":""},
{"code":"2196","theta":"","conductivity":""},
{"code":"2197","theta":"","conductivity":""},
{"code":"2198","theta":"","conductivity":""},
{"code":"2200","theta":"","conductivity":""},
{"code":"2201","theta":"","conductivity":""},
{"code":"2202","theta":"","conductivity":""},
{"code":"2203","theta":"","conductivity":""},
{"code":"2210","theta":"","conductivity":""},
{"code":"2211","theta":"","conductivity":""},
{"code":"2212","theta":"","conductivity":""},
{"code":"2213","theta":"","conductivity":""},
{"code":"2214","theta":"","conductivity":""},
{"code":"2215","theta":"","conductivity":""},
{"code":"2216","theta":"","conductivity":""},
{"code":"2217","theta":"","conductivity":""},
{"code":"2220","theta":"","conductivity":""},
{"code":"2221","theta":"","conductivity":""},
{"code":"2230","theta":"","conductivity":""},
{"code":"2231","theta":"","conductivity":""},
{"code":"2232","theta":"","conductivity":""},
{"code":"2240","theta":"","conductivity":""},
{"code":"2241","theta":"","conductivity":""},
{"code":"2242","theta":"","conductivity":""},
{"code":"2243","theta":"","conductivity":""},
{"code":"2250","theta":"","conductivity":""},
{"code":"2251","theta":"","conductivity":""},
{"code":"2252","theta":"","conductivity":""},
{"code":"2253","theta":"","conductivity":""},
{"code":"2260","theta":"","conductivity":""},
{"code":"2261","theta":"","conductivity":""},
{"code":"2262","theta":"","conductivity":""},
{"code":"2270","theta":"","conductivity":""},
{"code":"2271","theta":"","conductivity":""},
{"code":"2272","theta":"","conductivity":""},
{"code":"2273","theta":"","conductivity":""},
{"code":"2280","theta":"","conductivity":""},
{"code":"2281","theta":"","conductivity":""},
{"code":"2282","theta":"","conductivity":""},
{"code":"2283","theta":"","conductivity":""},
{"code":"2290","theta":"","conductivity":""},
{"code":"2291","theta":"","conductivity":""},
{"code":"2292","theta":"","conductivity":""},
{"code":"2293","theta":"","conductivity":""},
{"code":"2300","theta":"","conductivity":""},
{"code":"2301","theta":"","conductivity":""},
{"code":"2302","theta":"","conductivity":""},
{"code":"2303","theta":"","conductivity":""},
{"code":"2304","theta":"","conductivity":""},
{"code":"2305","theta":"","conductivity":""},
{"code":"2306","theta":"","conductivity":""},
{"code":"2307","theta":"","conductivity":""},
{"code":"2310","theta":"","conductivity":""},
{"code":"2320","theta":"","conductivity":""},
{"code":"2321","theta":"","conductivity":""},
{"code":"2330","theta":"","conductivity":""},
{"code":"2331","theta":"","conductivity":""},
{"code":"2332","theta":"","conductivity":""},
{"code":"2333","theta":"","conductivity":""},
{"code":"2334","theta":"","conductivity":""},
{"code":"2340","theta":"","conductivity":""},
{"code":"2341","theta":"","conductivity":""},
{"code":"2342","theta":"","conductivity":""},
{"code":"2350","theta":"","conductivity":""},
{"code":"2351","theta":"","conductivity":""},
{"code":"2360","theta":"","conductivity":""},
{"code":"2361","theta":"","conductivity":""},
{"code":"2362","theta":"","conductivity":""},
{"code":"2370","theta":"","conductivity":""},
{"code":"2371","theta":"","conductivity":""},
{"code":"2372","theta":"","conductivity":""},
{"code":"2373","theta":"","conductivity":""},
{"code":"2374","theta":"","conductivity":""},
{"code":"2380","theta":"","conductivity":""},
{"code":"2381","theta":"","conductivity":""},
{"code":"2382","theta":"","conductivity":""},
{"code":"2383","theta":"","conductivity":""},
{"code":"2384","theta":"","conductivity":""},
{"code":"2385","theta":"","conductivity":""},
{"code":"2390","theta":"","conductivity":""},
{"code":"2391","theta":"","conductivity":""},
{"code":"2392","theta":"","conductivity":""},
{"code":"2393","theta":"","conductivity":""},
{"code":"2394","theta":"","conductivity":""},
{"code":"2395","theta":"","conductivity":""},
{"code":"2400","theta":"","conductivity":""},
{"code":"2401","theta":"","conductivity":""},
{"code":"2402","theta":"","conductivity":""},
{"code":"2403","theta":"","conductivity":""},
{"code":"2404","theta":"","conductivity":""},
{"code":"2405","theta":"","conductivity":""},
{"code":"2410","theta":"","conductivity":""},
{"code":"2411","theta":"","conductivity":""},
{"code":"2412","theta":"","conductivity":""},
{"code":"2413","theta":"","conductivity":""},
{"code":"2414","theta":"","conductivity":""},
{"code":"2415","theta":"","conductivity":""},
{"code":"2420","theta":"","conductivity":""},
{"code":"2421","theta":"","conductivity":""},
{"code":"2422","theta":"","conductivity":""},
{"code":"2423","theta":"","conductivity":""},
{"code":"2424","theta":"","conductivity":""},
{"code":"2425","theta":"","conductivity":""},
{"code":"2430","theta":"","conductivity":""},
{"code":"2431","theta":"","conductivity":""},
{"code":"2432","theta":"","conductivity":""},
{"code":"2433","theta":"","conductivity":""},
{"code":"2434","theta":"","conductivity":""},
{"code":"2435","theta":"","conductivity":""},
{"code":"2440","theta":"","conductivity":""},
{"code":"2441","theta":"","conductivity":""},
{"code":"2442","theta":"","conductivity":""},
{"code":"2443","theta":"","conductivity":""},
{"code":"2444","theta":"","conductivity":""},
{"code":"2445","theta":"","conductivity":""},
{"code":"2450","theta":"","conductivity":""},
{"code":"2451","theta":"","conductivity":""},
{"code":"2452","theta":"","conductivity":""},
{"code":"2453","theta":"","conductivity":""},
{"code":"2454","theta":"","conductivity":""},
{"code":"2455","theta":"","conductivity":""},
{"code":"2460","theta":"","conductivity":""},
{"code":"2461","theta":"","conductivity":""},
{"code":"2462","theta":"","conductivity":""},
{"code":"2463","theta":"","conductivity":""},
{"code":"2464","theta":"","conductivity":""},
{"code":"2470","theta":"","conductivity":""},
{"code":"2471","theta":"","conductivity":""},
{"code":"2472","theta":"","conductivity":""},
{"code":"2480","theta":"","conductivity":""},
{"code":"2481","theta":"","conductivity":""},
{"code":"2482","theta":"","conductivity":""},
{"code":"2483","theta":"","conductivity":""},
{"code":"2491","theta":"","conductivity":""},
{"code":"2492","theta":"","conductivity":""},
{"code":"2493","theta":"","conductivity":""},
{"code":"2530","theta":"","conductivity":""},
{"code":"2531","theta":"","conductivity":""},
{"code":"2532","theta":"","conductivity":""},
{"code":"2540","theta":"","conductivity":""},
{"code":"2541","theta":"","conductivity":""},
{"code":"2542","theta":"","conductivity":""},
{"code":"2550","theta":"","conductivity":""},
{"code":"2551","theta":"","conductivity":""},
{"code":"2552","theta":"","conductivity":""},
{"code":"2560","theta":"","conductivity":""},
{"code":"2561","theta":"","conductivity":""},
{"code":"2562","theta":"","conductivity":""},
{"code":"2570","theta":"","conductivity":""},
{"code":"2571","theta":"","conductivity":""},
{"code":"2572","theta":"","conductivity":""},
{"code":"2573","theta":"","conductivity":""},
{"code":"2574","theta":"","conductivity":""},
{"code":"2580","theta":"","conductivity":""},
{"code":"2581","theta":"","conductivity":""},
{"code":"2582","theta":"","conductivity":""},
{"code":"2583","theta":"","conductivity":""},
{"code":"2584","theta":"","conductivity":""},
{"code":"2590","theta":"","conductivity":""},
{"code":"2591","theta":"","conductivity":""},
{"code":"2592","theta":"","conductivity":""},
{"code":"2593","theta":"","conductivity":""},
{"code":"2600","theta":"","conductivity":""},
{"code":"2601","theta":"","conductivity":""},
{"code":"2602","theta":"","conductivity":""},
{"code":"2603","theta":"","conductivity":""},
{"code":"2604","theta":"","conductivity":""},
{"code":"2605","theta":"","conductivity":""},
{"code":"2610","theta":"","conductivity":""},
{"code":"2611","theta":"","conductivity":""},
{"code":"2612","theta":"","conductivity":""},
{"code":"2613","theta":"","conductivity":""},
{"code":"2614","theta":"","conductivity":""},
{"code":"2620","theta":"","conductivity":""},
{"code":"2621","theta":"","conductivity":""},
{"code":"2622","theta":"","conductivity":""},
{"code":"2630","theta":"","conductivity":""},
{"code":"2631","theta":"","conductivity":""},
{"code":"2640","theta":"","conductivity":""},
{"code":"2641","theta":"","conductivity":""},
{"code":"2642","theta":"","conductivity":""},
{"code":"2650","theta":"","conductivity":""},
{"code":"2651","theta":"","conductivity":""},
{"code":"2652","theta":"","conductivity":""},
{"code":"2653","theta":"","conductivity":""},
{"code":"2660","theta":"","conductivity":""},
{"code":"2661","theta":"","conductivity":""},
{"code":"2670","theta":"","conductivity":""},
{"code":"2671","theta":"","conductivity":""},
{"code":"2672","theta":"","conductivity":""},
{"code":"2680","theta":"","conductivity":""},
{"code":"2681","theta":"","conductivity":""},
{"code":"2682","theta":"","conductivity":""},
{"code":"2683","theta":"","conductivity":""},
{"code":"2690","theta":"","conductivity":""},
{"code":"2691","theta":"","conductivity":""},
{"code":"2700","theta":"","conductivity":""},
{"code":"2701","theta":"","conductivity":""},
{"code":"2710","theta":"","conductivity":""},
{"code":"2711","theta":"","conductivity":""},
{"code":"2712","theta":"","conductivity":""},
{"code":"2713","theta":"","conductivity":""},
{"code":"2720","theta":"","conductivity":""},
{"code":"2721","theta":"","conductivity":""},
{"code":"2722","theta":"","conductivity":""},
{"code":"2723","theta":"","conductivity":""},
{"code":"2730","theta":"","conductivity":""},
{"code":"2731","theta":"","conductivity":""},
{"code":"2732","theta":"","conductivity":""},
{"code":"2740","theta":"","conductivity":""},
{"code":"2741","theta":"","conductivity":""},
{"code":"2742","theta":"","conductivity":""},
{"code":"2743","theta":"","conductivity":""},
{"code":"2750","theta":"","conductivity":""},
{"code":"2751","theta":"","conductivity":""},
{"code":"2752","theta":"","conductivity":""},
{"code":"2753","theta":"","conductivity":""},
{"code":"2760","theta":"","conductivity":""},
{"code":"2761","theta":"","conductivity":""},
{"code":"2762","theta":"","conductivity":""},
{"code":"2763","theta":"","conductivity":""},
{"code":"2764","theta":"","conductivity":""},
{"code":"2765","theta":"","conductivity":""},
{"code":"3000","theta":"","conductivity":""},
{"code":"3010","theta":"","conductivity":""},
{"code":"3020","theta":"","conductivity":""},
{"code":"3030","theta":"","conductivity":""},
{"code":"3031","theta":"","conductivity":""},
{"code":"3032","theta":"","conductivity":""},
{"code":"3033","theta":"","conductivity":""},
{"code":"3050","theta":"","conductivity":""},
{"code":"3060","theta":"","conductivity":""},
{"code":"3070","theta":"","conductivity":""},
{"code":"3080","theta":"","conductivity":""},
{"code":"3090","theta":"","conductivity":""},
{"code":"3091","theta":"","conductivity":""},
{"code":"3093","theta":"","conductivity":""},
{"code":"3100","theta":"","conductivity":""},
{"code":"3101","theta":"","conductivity":""},
{"code":"3102","theta":"","conductivity":""},
{"code":"3103","theta":"","conductivity":""},
{"code":"3110","theta":"","conductivity":""},
{"code":"3111","theta":"","conductivity":""},
{"code":"3112","theta":"","conductivity":""},
{"code":"3113","theta":"","conductivity":""},
{"code":"3120","theta":"","conductivity":""},
{"code":"3130","theta":"","conductivity":""},
{"code":"3131","theta":"","conductivity":""},
{"code":"3132","theta":"","conductivity":""},
{"code":"3133","theta":"","conductivity":""},
{"code":"3134","theta":"","conductivity":""},
{"code":"3140","theta":"","conductivity":""},
{"code":"3141","theta":"","conductivity":""},
{"code":"3142","theta":"","conductivity":""},
{"code":"3143","theta":"","conductivity":""},
{"code":"3144","theta":"","conductivity":""},
{"code":"3150","theta":"","conductivity":""},
{"code":"3151","theta":"","conductivity":""},
{"code":"3152","theta":"","conductivity":""},
{"code":"3153","theta":"","conductivity":""},
{"code":"3154","theta":"","conductivity":""},
{"code":"3155","theta":"","conductivity":""},
{"code":"3160","theta":"","conductivity":""},
{"code":"3161","theta":"","conductivity":""},
{"code":"3162","theta":"","conductivity":""},
{"code":"3163","theta":"","conductivity":""},
{"code":"3164","theta":"","conductivity":""},
{"code":"3165","theta":"","conductivity":""},
{"code":"3170","theta":"","conductivity":""},
{"code":"3171","theta":"","conductivity":""},
{"code":"3172","theta":"","conductivity":""},
{"code":"3173","theta":"","conductivity":""},
{"code":"3174","theta":"","conductivity":""},
{"code":"3175","theta":"","conductivity":""},
{"code":"3180","theta":"","conductivity":""},
{"code":"3181","theta":"","conductivity":""},
{"code":"3182","theta":"","conductivity":""},
{"code":"3183","theta":"","conductivity":""},
{"code":"3190","theta":"","conductivity":""},
{"code":"3191","theta":"","conductivity":""},
{"code":"3192","theta":"","conductivity":""},
{"code":"3193","theta":"","conductivity":""},
{"code":"3194","theta":"","conductivity":""},
{"code":"3195","theta":"","conductivity":""},
{"code":"3200","theta":"","conductivity":""},
{"code":"3201","theta":"","conductivity":""},
{"code":"3202","theta":"","conductivity":""},
{"code":"3203","theta":"","conductivity":""},
{"code":"3204","theta":"","conductivity":""},
{"code":"3205","theta":"","conductivity":""},
{"code":"3206","theta":"","conductivity":""},
{"code":"3210","theta":"","conductivity":""},
{"code":"3211","theta":"","conductivity":""},
{"code":"3212","theta":"","conductivity":""},
{"code":"3213","theta":"","conductivity":""},
{"code":"3214","theta":"","conductivity":""},
{"code":"3220","theta":"","conductivity":""},
{"code":"3221","theta":"","conductivity":""},
{"code":"3222","theta":"","conductivity":""},
{"code":"3223","theta":"","conductivity":""},
{"code":"3224","theta":"","conductivity":""},
{"code":"3225","theta":"","conductivity":""},
{"code":"3230","theta":"","conductivity":""},
{"code":"3231","theta":"","conductivity":""},
{"code":"3232","theta":"","conductivity":""},
{"code":"3240","theta":"","conductivity":""},
{"code":"3241","theta":"","conductivity":""},
{"code":"3242","theta":"","conductivity":""},
{"code":"3243","theta":"","conductivity":""},
{"code":"3250","theta":"","conductivity":""},
{"code":"3251","theta":"","conductivity":""},
{"code":"3252","theta":"","conductivity":""},
{"code":"3253","theta":"","conductivity":""},
{"code":"3260","theta":"","conductivity":""},
{"code":"3261","theta":"","conductivity":""},
{"code":"3262","theta":"","conductivity":""},
{"code":"3263","theta":"","conductivity":""},
{"code":"3264","theta":"","conductivity":""},
{"code":"3270","theta":"","conductivity":""},
{"code":"3271","theta":"","conductivity":""},
{"code":"3272","theta":"","conductivity":""},
{"code":"3273","theta":"","conductivity":""},
{"code":"3274","theta":"","conductivity":""},
{"code":"3281","theta":"","conductivity":""},
{"code":"3282","theta":"","conductivity":""},
{"code":"3283","theta":"","conductivity":""},
{"code":"3290","theta":"","conductivity":""},
{"code":"3291","theta":"","conductivity":""},
{"code":"3292","theta":"","conductivity":""},
{"code":"3293","theta":"","conductivity":""},
{"code":"3300","theta":"","conductivity":""},
{"code":"3301","theta":"","conductivity":""},
{"code":"3302","theta":"","conductivity":""},
{"code":"3303","theta":"","conductivity":""},
{"code":"3310","theta":"","conductivity":""},
{"code":"3311","theta":"","conductivity":""},
{"code":"3312","theta":"","conductivity":""},
{"code":"3313","theta":"","conductivity":""},
{"code":"3320","theta":"","conductivity":""},
{"code":"3321","theta":"","conductivity":""},
{"code":"3322","theta":"","conductivity":""},
{"code":"3323","theta":"","conductivity":""},
{"code":"3330","theta":"","conductivity":""},
{"code":"3331","theta":"","conductivity":""},
{"code":"3332","theta":"","conductivity":""},
{"code":"3340","theta":"","conductivity":""},
{"code":"3341","theta":"","conductivity":""},
{"code":"3350","theta":"","conductivity":""},
{"code":"3351","theta":"","conductivity":""},
{"code":"3360","theta":"","conductivity":""},
{"code":"3361","theta":"","conductivity":""},
{"code":"3370","theta":"","conductivity":""},
{"code":"3371","theta":"","conductivity":""},
{"code":"3380","theta":"","conductivity":""},
{"code":"3381","theta":"","conductivity":""},
{"code":"3390","theta":"","conductivity":""},
{"code":"3391","theta":"","conductivity":""},
{"code":"3392","theta":"","conductivity":""},
{"code":"3393","theta":"","conductivity":""},
{"code":"3395","theta":"","conductivity":""},
{"code":"4000","theta":"","conductivity":""},
{"code":"4001","theta":"","conductivity":""},
{"code":"4010","theta":"","conductivity":""},
{"code":"4011","theta":"","conductivity":""},
{"code":"4020","theta":"","conductivity":""},
{"code":"4021","theta":"","conductivity":""},
{"code":"4030","theta":"","conductivity":""},
{"code":"4031","theta":"","conductivity":""},
{"code":"4032","theta":"","conductivity":""},
{"code":"4033","theta":"","conductivity":""},
{"code":"4040","theta":"","conductivity":""},
{"code":"4041","theta":"","conductivity":""},
{"code":"4042","theta":"","conductivity":""},
{"code":"4043","theta":"","conductivity":""},
{"code":"4050","theta":"","conductivity":""},
{"code":"4051","theta":"","conductivity":""},
{"code":"4052","theta":"","conductivity":""},
{"code":"4060","theta":"","conductivity":""},
{"code":"4061","theta":"","conductivity":""},
{"code":"4062","theta":"","conductivity":""},
{"code":"4070","theta":"","conductivity":""},
{"code":"4071","theta":"","conductivity":""},
{"code":"4080","theta":"","conductivity":""},
{"code":"4081","theta":"","conductivity":""},
{"code":"4082","theta":"","conductivity":""},
{"code":"4090","theta":"","conductivity":""},
{"code":"4091","theta":"","conductivity":""},
{"code":"4092","theta":"","conductivity":""},
{"code":"4100","theta":"","conductivity":""},
{"code":"4101","theta":"","conductivity":""},
{"code":"4102","theta":"","conductivity":""},
{"code":"4110","theta":"","conductivity":""},
{"code":"4111","theta":"","conductivity":""},
{"code":"4112","theta":"","conductivity":""},
{"code":"4120","theta":"","conductivity":""},
{"code":"4121","theta":"","conductivity":""},
{"code":"4130","theta":"","conductivity":""},
{"code":"4131","theta":"","conductivity":""},
{"code":"4132","theta":"","conductivity":""},
{"code":"4140","theta":"","conductivity":""},
{"code":"4141","theta":"","conductivity":""},
{"code":"4142","theta":"","conductivity":""},
{"code":"4150","theta":"","conductivity":""},
{"code":"4151","theta":"","conductivity":""},
{"code":"4152","theta":"","conductivity":""},
{"code":"4160","theta":"","conductivity":""},
{"code":"4161","theta":"","conductivity":""},
{"code":"4162","theta":"","conductivity":""},
{"code":"4170","theta":"","conductivity":""},
{"code":"4171","theta":"","conductivity":""},
{"code":"4172","theta":"","conductivity":""},
{"code":"4180","theta":"","conductivity":""},
{"code":"4181","theta":"","conductivity":""},
{"code":"4182","theta":"","conductivity":""},
{"code":"4183","theta":"","conductivity":""},
{"code":"4190","theta":"","conductivity":""},
{"code":"4191","theta":"","conductivity":""},
{"code":"4192","theta":"","conductivity":""},
{"code":"4193","theta":"","conductivity":""},
{"code":"4194","theta":"","conductivity":""},
{"code":"4195","theta":"","conductivity":""},
{"code":"4200","theta":"","conductivity":""},
{"code":"4201","theta":"","conductivity":""},
{"code":"4202","theta":"","conductivity":""},
{"code":"4203","theta":"","conductivity":""},
{"code":"4204","theta":"","conductivity":""},
{"code":"4210","theta":"","conductivity":""},
{"code":"4211","theta":"","conductivity":""},
{"code":"4212","theta":"","conductivity":""},
{"code":"4213","theta":"","conductivity":""},
{"code":"4220","theta":"","conductivity":""},
{"code":"4221","theta":"","conductivity":""},
{"code":"4222","theta":"","conductivity":""},
{"code":"4223","theta":"","conductivity":""},
{"code":"4224","theta":"","conductivity":""},
{"code":"4230","theta":"","conductivity":""},
{"code":"4231","theta":"","conductivity":""},
{"code":"4232","theta":"","conductivity":""},
{"code":"4233","theta":"","conductivity":""},
{"code":"4234","theta":"","conductivity":""},
{"code":"4241","theta":"","conductivity":""},
{"code":"4242","theta":"","conductivity":""},
{"code":"4243","theta":"","conductivity":""},
{"code":"4251","theta":"","conductivity":""},
{"code":"4252","theta":"","conductivity":""},
{"code":"4253","theta":"","conductivity":""},
{"code":"4261","theta":"","conductivity":""},
{"code":"4262","theta":"","conductivity":""},
{"code":"4263","theta":"","conductivity":""},
{"code":"4271","theta":"","conductivity":""},
{"code":"4272","theta":"","conductivity":""},
{"code":"4273","theta":"","conductivity":""},
{"code":"4281","theta":"","conductivity":""},
{"code":"4282","theta":"","conductivity":""},
{"code":"4283","theta":"","conductivity":""},
{"code":"4284","theta":"","conductivity":""},
{"code":"4291","theta":"","conductivity":""},
{"code":"4310","theta":"","conductivity":""},
{"code":"4311","theta":"","conductivity":""},
{"code":"4340","theta":"","conductivity":""},
{"code":"4341","theta":"","conductivity":""},
{"code":"4390","theta":"","conductivity":""},
{"code":"4391","theta":"","conductivity":""},
{"code":"4410","theta":"","conductivity":""},
{"code":"4411","theta":"","conductivity":""},
{"code":"4412","theta":"","conductivity":""},
{"code":"4440","theta":"","conductivity":""},
{"code":"4441","theta":"","conductivity":""},
{"code":"4442","theta":"","conductivity":""},
{"code":"4443","theta":"","conductivity":""},
{"code":"4444","theta":"","conductivity":""},
{"code":"4445","theta":"","conductivity":""},
{"code":"4450","theta":"","conductivity":""},
{"code":"4460","theta":"","conductivity":""},
{"code":"4470","theta":"","conductivity":""},
{"code":"4480","theta":"","conductivity":""},
{"code":"4490","theta":"","conductivity":""},
{"code":"4500","theta":"","conductivity":""},
{"code":"4510","theta":"","conductivity":""},
{"code":"4511","theta":"","conductivity":""},
{"code":"4512","theta":"","conductivity":""},
{"code":"4514","theta":"","conductivity":""},
{"code":"4520","theta":"","conductivity":""},
{"code":"4521","theta":"","conductivity":""},
{"code":"4522","theta":"","conductivity":""},
{"code":"4523","theta":"","conductivity":""},
{"code":"4530","theta":"","conductivity":""},
{"code":"4531","theta":"","conductivity":""},
{"code":"4532","theta":"","conductivity":""},
{"code":"4533","theta":"","conductivity":""},
{"code":"4540","theta":"","conductivity":""},
{"code":"4541","theta":"","conductivity":""},
{"code":"4542","theta":"","conductivity":""},
{"code":"4543","theta":"","conductivity":""},
{"code":"4544","theta":"","conductivity":""},
{"code":"4550","theta":"","conductivity":""},
{"code":"4551","theta":"","conductivity":""},
{"code":"4552","theta":"","conductivity":""},
{"code":"4553","theta":"","conductivity":""},
{"code":"4560","theta":"","conductivity":""},
{"code":"4561","theta":"","conductivity":""},
{"code":"4562","theta":"","conductivity":""},
{"code":"4564","theta":"","conductivity":""},
{"code":"4570","theta":"","conductivity":""},
{"code":"4571","theta":"","conductivity":""},
{"code":"4572","theta":"","conductivity":""},
{"code":"4573","theta":"","conductivity":""},
{"code":"4574","theta":"","conductivity":""},
{"code":"4575","theta":"","conductivity":""},
{"code":"4580","theta":"","conductivity":""},
{"code":"4581","theta":"","conductivity":""},
{"code":"4582","theta":"","conductivity":""},
{"code":"4583","theta":"","conductivity":""},
{"code":"4590","theta":"","conductivity":""},
{"code":"4591","theta":"","conductivity":""},
{"code":"4592","theta":"","conductivity":""},
{"code":"4600","theta":"","conductivity":""},
{"code":"4601","theta":"","conductivity":""},
{"code":"4602","theta":"","conductivity":""},
{"code":"4610","theta":"","conductivity":""},
{"code":"4611","theta":"","conductivity":""},
{"code":"4612","theta":"","conductivity":""},
{"code":"4620","theta":"","conductivity":""},
{"code":"4621","theta":"","conductivity":""},
{"code":"4622","theta":"","conductivity":""},
{"code":"4650","theta":"","conductivity":""},
{"code":"4651","theta":"","conductivity":""},
{"code":"4660","theta":"","conductivity":""},
{"code":"4661","theta":"","conductivity":""},
{"code":"4670","theta":"","conductivity":""},
{"code":"4671","theta":"","conductivity":""},
{"code":"4672","theta":"","conductivity":""},
{"code":"4673","theta":"","conductivity":""},
{"code":"4680","theta":"","conductivity":""},
{"code":"4681","theta":"","conductivity":""},
{"code":"4690","theta":"","conductivity":""},
{"code":"4700","theta":"","conductivity":""},
{"code":"4710","theta":"","conductivity":""},
{"code":"4720","theta":"","conductivity":""},
{"code":"4750","theta":"","conductivity":""},
{"code":"4760","theta":"","conductivity":""},
{"code":"4770","theta":"","conductivity":""},
{"code":"4780","theta":"","conductivity":""},
{"code":"4790","theta":"","conductivity":""},
{"code":"4791","theta":"","conductivity":""},
{"code":"4800","theta":"","conductivity":""},
{"code":"4801","theta":"","conductivity":""},
{"code":"4810","theta":"","conductivity":""},
{"code":"4870","theta":"","conductivity":""},
{"code":"4880","theta":"","conductivity":""},
{"code":"4881","theta":"","conductivity":""},
{"code":"4890","theta":"","conductivity":""},
{"code":"4910","theta":"","conductivity":""},
{"code":"4920","theta":"","conductivity":""},
{"code":"4921","theta":"","conductivity":""},
{"code":"4922","theta":"","conductivity":""},
{"code":"4923","theta":"","conductivity":""},
{"code":"4940","theta":"","conductivity":""},
{"code":"4941","theta":"","conductivity":""},
{"code":"4950","theta":"","conductivity":""},
{"code":"4960","theta":"","conductivity":""}]
