[{"code":"1010","theta":"","conductivity":""},
{"code":"1011","theta":"","conductivity":""},
{"code":"1012","theta":"","conductivity":""},
{"code":"1013","theta":"","conductivity":""},
{"code":"1014","theta":"","conductivity":""},
{"code":"1015","theta":"","conductivity":""},
{"code":"1020","theta":"","conductivity":""},
{"code":"1021","theta":"","conductivity":""},
{"code":"1022","theta":"","conductivity":""},
{"code":"1023","theta":"","conductivity":""},
{"code":"1024","theta":"","conductivity":""},
{"code":"1030","theta":"","conductivity":""},
{"code":"1031","theta":"","conductivity":""},
{"code":"1032","theta":"","conductivity":""},
{"code":"1040","theta":"","conductivity":""},
{"code":"1041","theta":"","conductivity":""},
{"code":"1042","theta":"","conductivity":""},
{"code":"1043","theta":"","conductivity":""},
{"code":"1050","theta":"","conductivity":""},
{"code":"1051","theta":"","conductivity":""},
{"code":"1052","theta":"","conductivity":""},
{"code":"1053","theta":"","conductivity":""},
{"code":"1054","theta":"","conductivity":""},
{"code":"1060","theta":"","conductivity":""},
{"code":"1061","theta":"","conductivity":""},
{"code":"1062","theta":"","conductivity":""},
{"code":"1063","theta":"","conductivity":""},
{"code":"1070","theta":"","conductivity":""},
{"code":"1071","theta":"","conductivity":""},
{"code":"1072","theta":"","conductivity":""},
{"code":"1073","theta":"","conductivity":""},
{"code":"1074","theta":"","conductivity":""},
{"code":"1075","theta":"","conductivity":""},
{"code":"1080","theta":"","conductivity":""},
{"code":"1081","theta":"","conductivity":""},
{"code":"1082","theta":"","conductivity":""},
{"code":"1083","theta":"","conductivity":""},
{"code":"1084","theta":"","conductivity":""},
{"code":"1085","theta":"","conductivity":""},
{"code":"1086","theta":"","conductivity":""},
{"code":"1087","theta":"","conductivity":""},
{"code":"1090","theta":"","conductivity":""},
{"code":"1091","theta":"","conductivity":""},
{"code":"1092","theta":"","conductivity":""},
{"code":"1100","theta":"","conductivity":""},
{"code":"1101","theta":"","conductivity":""},
{"code":"1102","theta":"","conductivity":""},
{"code":"1103","theta":"","conductivity":""},
{"code":"1104","theta":"","conductivity":""},
{"code":"1110","theta":"","conductivity":""},
{"code":"1111","theta":"","conductivity":""},
{"code":"1112","theta":"","conductivity":""},
{"code":"1113","theta":"","conductivity":""},
{"code":"1114","theta":"","conductivity":""},
{"code":"1115","theta":"","conductivity":""},
{"code":"1116","theta":"","conductivity":""},
{"code":"1117","theta":"","conductivity":""},
{"code":"1120","theta":"","conductivity":""},
{"code":"1121","theta":"","conductivity":""},
{"code":"1122","theta":"","conductivity":""},
{"code":"1123","theta":"","conductivity":""},
{"code":"1130","theta":"","conductivity":""},
{"code":"1131","theta":"","conductivity":""},
{"code":"1132","theta":"","conductivity":""},
{"code":"1133","theta":"","conductivity":""},
{"code":"1134","theta":"","conductivity":""},
{"code":"1135","theta":"","conductivity":""},
{"code":"1140","theta":"","conductivity":""},
{"code":"1141","theta":"","conductivity":""},
{"code":"1142","theta":"","conductivity":""},
{"code":"1143","theta":"","conductivity":""},
{"code":"1150","theta":"","conductivity":""},
{"code":"1151","theta":"","conductivity":""},
{"code":"1152","theta":"","conductivity":""},
{"code":"1160","theta":"","conductivity":""},
{"code":"1161","theta":"","conductivity":""},
{"code":"1162","theta":"","conductivity":""},
{"code":"1163","theta":"","conductivity":""},
{"code":"1164","theta":"","conductivity":""},
{"code":"1165","theta":"","conductivity":""},
{"code":"1166","theta":"","conductivity":""},
{"code":"1170","theta":"","conductivity":""},
{"code":"1171","theta":"","conductivity":""},
{"code":"1172","theta":"","conductivity":""},
{"code":"1173","theta":"","conductivity":""},
{"code":"1174","theta":"","conductivity":""},
{"code":"1180","theta":"","conductivity":""},
{"code":"1181","theta":"","conductivity":""},
{"code":"1182","theta":"","conductivity":""},
{"code":"1183","theta":"","conductivity":""},
{"code":"1184","theta":"","conductivity":""},
{"code":"1190","theta":"","conductivity":""},
{"code":"1191","theta":"","conductivity":""},
{"code":"1192","theta":"","conductivity":""},
{"code":"1193","theta":"","conductivity":""},
{"code":"1194","theta":"","conductivity":""},
{"code":"1200","theta":"","conductivity":""},
{"code":"1201","theta":"","conductivity":""},
{"code":"1202","theta":"","conductivity":""},
{"code":"1203","theta":"","conductivity":""},
{"code":"1204","theta":"","conductivity":""},
{"code":"1210","theta":"","conductivity":""},
{"code":"1211","theta":"","conductivity":""},
{"code":"1212","theta":"","conductivity":""},
{"code":"1213","theta":"","conductivity":""},
{"code":"1220","theta":"","conductivity":""},
{"code":"1221","theta":"","conductivity":""},
{"code":"1222","theta":"","conductivity":""},
{"code":"1223","theta":"","conductivity":""},
{"code":"1224","theta":"","conductivity":""},
{"code":"1225","theta":"","conductivity":""},
{"code":"1230","theta":"","conductivity":""},
{"code":"1231","theta":"","conductivity":""},
{"code":"1232","theta":"","conductivity":""},
{"code":"1233","theta":"","conductivity":""},
{"code":"1234","theta":"","conductivity":""},
{"code":"1235","theta":"","conductivity":""},
{"code":"1236","theta":"","conductivity":""},
{"code":"1237","theta":"","conductivity":""},
{"code":"1240","theta":"","conductivity":""},
{"code":"1241","theta":"","conductivity":""},
{"code":"1260","theta":"","conductivity":""},
{"code":"1261","theta":"","conductivity":""},
{"code":"1270","theta":"","conductivity":""},
{"code":"1280","theta":"","conductivity":""},
{"code":"1281","theta":"","conductivity":""},
{"code":"1282","theta":"","conductivity":""},
{"code":"1290","theta":"","conductivity":""},
{"code":"1300","theta":"0.38","conductivity":"16.8"},
{"code":"1300","theta":"0.37","conductivity":"13.44"},
{"code":"1300","theta":"0.35","conductivity":"4.8"},
{"code":"1300","theta":"0.345","conductivity":"2.16"},
{"code":"1301","theta":"0.38","conductivity":"16.32"},
{"code":"1301","theta":"0.37","conductivity":"12.24"},
{"code":"1301","theta":"0.36","conductivity":"6.24"},
{"code":"1301","theta":"0.34","conductivity":"1.608"},
{"code":"1301","theta":"0.32","conductivity":"0.552"},
{"code":"1301","theta":"0.315","conductivity":"0.1968"},
{"code":"1310","theta":"0.165","conductivity":"10.8"},
{"code":"1310","theta":"0.145","conductivity":"5.04"},
{"code":"1310","theta":"0.12","conductivity":"1.824"},
{"code":"1310","theta":"0.11","conductivity":"1.104"},
{"code":"1310","theta":"0.1","conductivity":"0.456"},
{"code":"1310","theta":"0.095","conductivity":"0.2232"},
{"code":"1310","theta":"0.085","conductivity":"0.1728"},
{"code":"1320","theta":"","conductivity":""},
{"code":"1330","theta":"","conductivity":""},
{"code":"1331","theta":"","conductivity":""},
{"code":"1340","theta":"","conductivity":""},
{"code":"1341","theta":"","conductivity":""},
{"code":"1342","theta":"","conductivity":""},
{"code":"1350","theta":"","conductivity":""},
{"code":"1351","theta":"","conductivity":""},
{"code":"1352","theta":"","conductivity":""},
{"code":"1360","theta":"","conductivity":""},
{"code":"1361","theta":"","conductivity":""},
{"code":"1362","theta":"","conductivity":""},
{"code":"1370","theta":"","conductivity":""},
{"code":"1371","theta":"","conductivity":""},
{"code":"1372","theta":"","conductivity":""},
{"code":"1380","theta":"","conductivity":""},
{"code":"1381","theta":"","conductivity":""},
{"code":"1382","theta":"","conductivity":""},
{"code":"1383","theta":"","conductivity":""},
{"code":"1390","theta":"","conductivity":""},
{"code":"1391","theta":"","conductivity":""},
{"code":"1392","theta":"","conductivity":""},
{"code":"1400","theta":"","conductivity":""},
{"code":"1410","theta":"0.211","conductivity":"233"},
{"code":"1410","theta":"0.221","conductivity":"276"},
{"code":"1410","theta":"0.227","conductivity":"415"},
{"code":"1410","theta":"0.228","conductivity":"363"},
{"code":"1410","theta":"0.235","conductivity":"423"},
{"code":"1410","theta":"0.236","conductivity":"302"},
{"code":"1410","theta":"0.238","conductivity":"432"},
{"code":"1410","theta":"0.24","conductivity":"458"},
{"code":"1410","theta":"0.259","conductivity":"734"},
{"code":"1410","theta":"0.262","conductivity":"406"},
{"code":"1410","theta":"0.266","conductivity":"397"},
{"code":"1410","theta":"0.27","conductivity":"354"},
{"code":"1410","theta":"0.367","conductivity":"2850"},
{"code":"1410","theta":"0.399","conductivity":"2850"},
{"code":"1410","theta":"0.431","conductivity":"3800"},
{"code":"1410","theta":"0.437","conductivity":"4670"},
{"code":"1420","theta":"","conductivity":""},
{"code":"1430","theta":"0.275","conductivity":"9.63"},
{"code":"1430","theta":"0.233","conductivity":"2.91"},
{"code":"1430","theta":"0.2","conductivity":"1.53"},
{"code":"1430","theta":"0.152","conductivity":"0.183"},
{"code":"1430","theta":"0.135","conductivity":"0.0276"},
{"code":"1440","theta":"0.302","conductivity":"0.02"},
{"code":"1440","theta":"0.282","conductivity":"0.013"},
{"code":"1440","theta":"0.264","conductivity":"0.0023"},
{"code":"1440","theta":"0.257","conductivity":"0.0012"},
{"code":"1440","theta":"0.252","conductivity":"0.00052"},
{"code":"1440","theta":"0.248","conductivity":"0.0004"},
{"code":"1440","theta":"0.245","conductivity":"2E-05"},
{"code":"1450","theta":"","conductivity":""},
{"code":"1460","theta":"","conductivity":""},
{"code":"1461","theta":"","conductivity":""},
{"code":"1462","theta":"","conductivity":""},
{"code":"1463","theta":"","conductivity":""},
{"code":"1464","theta":"","conductivity":""},
{"code":"1465","theta":"","conductivity":""},
{"code":"1466","theta":"","conductivity":""},
{"code":"1467","theta":"","conductivity":""},
{"code":"1480","theta":"","conductivity":""},
{"code":"1481","theta":"","conductivity":""},
{"code":"1482","theta":"","conductivity":""},
{"code":"1490","theta":"","conductivity":""},
{"code":"2000","theta":"","conductivity":""},
{"code":"2001","theta":"","conductivity":""},
{"code":"2002","theta":"","conductivity":""},
{"code":"2010","theta":"","conductivity":""},
{"code":"2011","theta":"","conductivity":""},
{"code":"2012","theta":"","conductivity":""},
{"code":"2020","theta":"","conductivity":""},
{"code":"2021","theta":"","conductivity":""},
{"code":"2022","theta":"","conductivity":""},
{"code":"2030","theta":"","conductivity":""},
{"code":"2031","theta":"","conductivity":""},
{"code":"2032","theta":"","conductivity":""},
{"code":"2040","theta":"","conductivity":""},
{"code":"2041","theta":"","conductivity":""},
{"code":"2050","theta":"","conductivity":""},
{"code":"2051","theta":"","conductivity":""},
{"code":"2060","theta":"","conductivity":""},
{"code":"2061","theta":"","conductivity":""},
{"code":"2070","theta":"","conductivity":""},
{"code":"2071","theta":"","conductivity":""},
{"code":"2080","theta":"","conductivity":""},
{"code":"2081","theta":"","conductivity":""},
{"code":"2090","theta":"","conductivity":""},
{"code":"2091","theta":"","conductivity":""},
{"code":"2092","theta":"","conductivity":""},
{"code":"2100","theta":"","conductivity":""},
{"code":"2101","theta":"","conductivity":""},
{"code":"2102","theta":"","conductivity":""},
{"code":"2103","theta":"","conductivity":""},
{"code":"2104","theta":"","conductivity":""},
{"code":"2105","theta":"","conductivity":""},
{"code":"2110","theta":"","conductivity":""},
{"code":"2111","theta":"","conductivity":""},
{"code":"2120","theta":"","conductivity":""},
{"code":"2121","theta":"","conductivity":""},
{"code":"2122","theta":"","conductivity":""},
{"code":"2123","theta":"","conductivity":""},
{"code":"2124","theta":"","conductivity":""},
{"code":"2125","theta":"","conductivity":""},
{"code":"2126","theta":"","conductivity":""},
{"code":"2130","theta":"","conductivity":""},
{"code":"2131","theta":"","conductivity":""},
{"code":"2132","theta":"","conductivity":""},
{"code":"2140","theta":"","conductivity":""},
{"code":"2141","theta":"0.4","conductivity":"173"},
{"code":"2141","theta":"0.382","conductivity":"168"},
{"code":"2141","theta":"0.369","conductivity":"138"},
{"code":"2141","theta":"0.344","conductivity":"73.4"},
{"code":"2141","theta":"0.338","conductivity":"104"},
{"code":"2141","theta":"0.33","conductivity":"69.1"},
{"code":"2141","theta":"0.323","conductivity":"73.4"},
{"code":"2141","theta":"0.318","conductivity":"56.2"},
{"code":"2141","theta":"0.312","conductivity":"53.6"},
{"code":"2141","theta":"0.308","conductivity":"70.8"},
{"code":"2141","theta":"0.291","conductivity":"51.8"},
{"code":"2141","theta":"0.287","conductivity":"43.2"},
{"code":"2141","theta":"0.285","conductivity":"47.5"},
{"code":"2141","theta":"0.281","conductivity":"38"},
{"code":"2141","theta":"0.275","conductivity":"30.2"},
{"code":"2141","theta":"0.267","conductivity":"38.9"},
{"code":"2141","theta":"0.265","conductivity":"32.8"},
{"code":"2141","theta":"0.264","conductivity":"26.8"},
{"code":"2141","theta":"0.258","conductivity":"39.7"},
{"code":"2141","theta":"0.253","conductivity":"27.6"},
{"code":"2141","theta":"0.251","conductivity":"20.7"},
{"code":"2141","theta":"0.239","conductivity":"19"},
{"code":"2141","theta":"0.236","conductivity":"12.1"},
{"code":"2141","theta":"0.234","conductivity":"9.07"},
{"code":"2141","theta":"0.228","conductivity":"14.7"},
{"code":"2141","theta":"0.224","conductivity":"10.72"},
{"code":"2141","theta":"0.222","conductivity":"7.26"},
{"code":"2141","theta":"0.215","conductivity":"9.5"},
{"code":"2141","theta":"0.214","conductivity":"7.34"},
{"code":"2141","theta":"0.21","conductivity":"8.232"},
{"code":"2141","theta":"0.208","conductivity":"8.64"},
{"code":"2141","theta":"0.204","conductivity":"5.88"},
{"code":"2141","theta":"0.203","conductivity":"4.289"},
{"code":"2141","theta":"0.194","conductivity":"3.72"},
{"code":"2141","theta":"0.186","conductivity":"2.94"},
{"code":"2141","theta":"0.179","conductivity":"2.25"},
{"code":"2141","theta":"0.178","conductivity":"1.47"},
{"code":"2141","theta":"0.175","conductivity":"0.57"},
{"code":"2141","theta":"0.169","conductivity":"1.81"},
{"code":"2141","theta":"0.164","conductivity":"0.32"},
{"code":"2141","theta":"0.148","conductivity":"0.058"},
{"code":"2141","theta":"0.109","conductivity":"0.0033"},
{"code":"2141","theta":"0.089","conductivity":"0.00095"},
{"code":"2150","theta":"0.428","conductivity":"181"},
{"code":"2150","theta":"0.42","conductivity":"220.2"},
{"code":"2150","theta":"0.405","conductivity":"190"},
{"code":"2150","theta":"0.369","conductivity":"217"},
{"code":"2150","theta":"0.365","conductivity":"125"},
{"code":"2150","theta":"0.36","conductivity":"56.51"},
{"code":"2150","theta":"0.32","conductivity":"119.9"},
{"code":"2150","theta":"0.305","conductivity":"16.49"},
{"code":"2150","theta":"0.298","conductivity":"14.19"},
{"code":"2150","theta":"0.264","conductivity":"1.927"},
{"code":"2150","theta":"0.262","conductivity":"6.404"},
{"code":"2150","theta":"0.245","conductivity":"1.68"},
{"code":"2150","theta":"0.24","conductivity":"5.008"},
{"code":"2150","theta":"0.232","conductivity":"1.037"},
{"code":"2150","theta":"0.23","conductivity":"1.05"},
{"code":"2150","theta":"0.207","conductivity":"0.393"},
{"code":"2150","theta":"0.2","conductivity":"0.156"},
{"code":"2151","theta":"0.305","conductivity":"90.7"},
{"code":"2151","theta":"0.303","conductivity":"82.1"},
{"code":"2151","theta":"0.3","conductivity":"181"},
{"code":"2151","theta":"0.292","conductivity":"173"},
{"code":"2151","theta":"0.291","conductivity":"99.4"},
{"code":"2151","theta":"0.29","conductivity":"259"},
{"code":"2151","theta":"0.23","conductivity":"43.2"},
{"code":"2151","theta":"0.225","conductivity":"60.5"},
{"code":"2151","theta":"0.185","conductivity":"15.4"},
{"code":"2151","theta":"0.175","conductivity":"10.4"},
{"code":"2151","theta":"0.115","conductivity":"14.2"},
{"code":"2151","theta":"0.102","conductivity":"1.137"},
{"code":"2151","theta":"0.076","conductivity":"0.253"},
{"code":"2151","theta":"0.075","conductivity":"0.32"},
{"code":"2160","theta":"","conductivity":""},
{"code":"2161","theta":"","conductivity":""},
{"code":"2170","theta":"","conductivity":""},
{"code":"2171","theta":"","conductivity":""},
{"code":"2180","theta":"","conductivity":""},
{"code":"2181","theta":"","conductivity":""},
{"code":"2190","theta":"","conductivity":""},
{"code":"2191","theta":"","conductivity":""},
{"code":"2192","theta":"","conductivity":""},
{"code":"2193","theta":"","conductivity":""},
{"code":"2194","theta":"","conductivity":""},
{"code":"2195","theta":"","conductivity":""},
{"code":"2196","theta":"","conductivity":""},
{"code":"2197","theta":"","conductivity":""},
{"code":"2198","theta":"","conductivity":""},
{"code":"2200","theta":"","conductivity":""},
{"code":"2201","theta":"","conductivity":""},
{"code":"2202","theta":"","conductivity":""},
{"code":"2203","theta":"","conductivity":""},
{"code":"2210","theta":"","conductivity":""},
{"code":"2211","theta":"","conductivity":""},
{"code":"2212","theta":"","conductivity":""},
{"code":"2213","theta":"","conductivity":""},
{"code":"2214","theta":"","conductivity":""},
{"code":"2215","theta":"","conductivity":""},
{"code":"2216","theta":"","conductivity":""},
{"code":"2217","theta":"","conductivity":""},
{"code":"2220","theta":"","conductivity":""},
{"code":"2221","theta":"","conductivity":""},
{"code":"2230","theta":"","conductivity":""},
{"code":"2231","theta":"","conductivity":""},
{"code":"2232","theta":"","conductivity":""},
{"code":"2240","theta":"","conductivity":""},
{"code":"2241","theta":"","conductivity":""},
{"code":"2242","theta":"","conductivity":""},
{"code":"2243","theta":"","conductivity":""},
{"code":"2250","theta":"","conductivity":""},
{"code":"2251","theta":"","conductivity":""},
{"code":"2252","theta":"","conductivity":""},
{"code":"2253","theta":"","conductivity":""},
{"code":"2260","theta":"","conductivity":""},
{"code":"2261","theta":"","conductivity":""},
{"code":"2262","theta":"","conductivity":""},
{"code":"2270","theta":"","conductivity":""},
{"code":"2271","theta":"","conductivity":""},
{"code":"2272","theta":"","conductivity":""},
{"code":"2273","theta":"","conductivity":""},
{"code":"2280","theta":"","conductivity":""},
{"code":"2281","theta":"","conductivity":""},
{"code":"2282","theta":"","conductivity":""},
{"code":"2283","theta":"","conductivity":""},
{"code":"2290","theta":"","conductivity":""},
{"code":"2291","theta":"","conductivity":""},
{"code":"2292","theta":"","conductivity":""},
{"code":"2293","theta":"","conductivity":""},
{"code":"2300","theta":"","conductivity":""},
{"code":"2301","theta":"","conductivity":""},
{"code":"2302","theta":"","conductivity":""},
{"code":"2303","theta":"","conductivity":""},
{"code":"2304","theta":"","conductivity":""},
{"code":"2305","theta":"","conductivity":""},
{"code":"2306","theta":"","conductivity":""},
{"code":"2307","theta":"","conductivity":""},
{"code":"2310","theta":"0.137","conductivity":"14"},
{"code":"2310","theta":"0.186","conductivity":"94.2"},
{"code":"2310","theta":"0.234","conductivity":"220"},
{"code":"2310","theta":"0.263","conductivity":"407"},
{"code":"2310","theta":"0.292","conductivity":"680"},
{"code":"2320","theta":"","conductivity":""},
{"code":"2321","theta":"","conductivity":""},
{"code":"2330","theta":"","conductivity":""},
{"code":"2331","theta":"","conductivity":""},
{"code":"2332","theta":"","conductivity":""},
{"code":"2333","theta":"","conductivity":""},
{"code":"2334","theta":"","conductivity":""},
{"code":"2340","theta":"","conductivity":""},
{"code":"2341","theta":"","conductivity":""},
{"code":"2342","theta":"","conductivity":""},
{"code":"2350","theta":"","conductivity":""},
{"code":"2351","theta":"","conductivity":""},
{"code":"2360","theta":"","conductivity":""},
{"code":"2361","theta":"","conductivity":""},
{"code":"2362","theta":"","conductivity":""},
{"code":"2370","theta":"","conductivity":""},
{"code":"2371","theta":"","conductivity":""},
{"code":"2372","theta":"","conductivity":""},
{"code":"2373","theta":"","conductivity":""},
{"code":"2374","theta":"","conductivity":""},
{"code":"2380","theta":"","conductivity":""},
{"code":"2381","theta":"","conductivity":""},
{"code":"2382","theta":"","conductivity":""},
{"code":"2383","theta":"","conductivity":""},
{"code":"2384","theta":"","conductivity":""},
{"code":"2385","theta":"","conductivity":""},
{"code":"2390","theta":"","conductivity":""},
{"code":"2391","theta":"","conductivity":""},
{"code":"2392","theta":"","conductivity":""},
{"code":"2393","theta":"","conductivity":""},
{"code":"2394","theta":"","conductivity":""},
{"code":"2395","theta":"","conductivity":""},
{"code":"2400","theta":"","conductivity":""},
{"code":"2401","theta":"","conductivity":""},
{"code":"2402","theta":"","conductivity":""},
{"code":"2403","theta":"","conductivity":""},
{"code":"2404","theta":"","conductivity":""},
{"code":"2405","theta":"","conductivity":""},
{"code":"2410","theta":"","conductivity":""},
{"code":"2411","theta":"","conductivity":""},
{"code":"2412","theta":"","conductivity":""},
{"code":"2413","theta":"","conductivity":""},
{"code":"2414","theta":"","conductivity":""},
{"code":"2415","theta":"","conductivity":""},
{"code":"2420","theta":"","conductivity":""},
{"code":"2421","theta":"","conductivity":""},
{"code":"2422","theta":"","conductivity":""},
{"code":"2423","theta":"","conductivity":""},
{"code":"2424","theta":"","conductivity":""},
{"code":"2425","theta":"","conductivity":""},
{"code":"2430","theta":"","conductivity":""},
{"code":"2431","theta":"","conductivity":""},
{"code":"2432","theta":"","conductivity":""},
{"code":"2433","theta":"","conductivity":""},
{"code":"2434","theta":"","conductivity":""},
{"code":"2435","theta":"","conductivity":""},
{"code":"2440","theta":"","conductivity":""},
{"code":"2441","theta":"","conductivity":""},
{"code":"2442","theta":"","conductivity":""},
{"code":"2443","theta":"","conductivity":""},
{"code":"2444","theta":"","conductivity":""},
{"code":"2445","theta":"","conductivity":""},
{"code":"2450","theta":"","conductivity":""},
{"code":"2451","theta":"","conductivity":""},
{"code":"2452","theta":"","conductivity":""},
{"code":"2453","theta":"","conductivity":""},
{"code":"2454","theta":"","conductivity":""},
{"code":"2455","theta":"","conductivity":""},
{"code":"2460","theta":"","conductivity":""},
{"code":"2461","theta":"","conductivity":""},
{"code":"2462","theta":"","conductivity":""},
{"code":"2463","theta":"","conductivity":""},
{"code":"2464","theta":"","conductivity":""},
{"code":"2470","theta":"","conductivity":""},
{"code":"2471","theta":"","conductivity":""},
{"code":"2472","theta":"","conductivity":""},
{"code":"2480","theta":"","conductivity":""},
{"code":"2481","theta":"","conductivity":""},
{"code":"2482","theta":"","conductivity":""},
{"code":"2483","theta":"","conductivity":""},
{"code":"2491","theta":"","conductivity":""},
{"code":"2492","theta":"","conductivity":""},
{"code":"2493","theta":"","conductivity":""},
{"code":"2530","theta":"","conductivity":""},
{"code":"2531","theta":"","conductivity":""},
{"code":"2532","theta":"","conductivity":""},
{"code":"2540","theta":"","conductivity":""},
{"code":"2541","theta":"","conductivity":""},
{"code":"2542","theta":"","conductivity":""},
{"code":"2550","theta":"","conductivity":""},
{"code":"2551","theta":"","conductivity":""},
{"code":"2552","theta":"","conductivity":""},
{"code":"2560","theta":"","conductivity":""},
{"code":"2561","theta":"","conductivity":""},
{"code":"2562","theta":"","conductivity":""},
{"code":"2570","theta":"","conductivity":""},
{"code":"2571","theta":"","conductivity":""},
{"code":"2572","theta":"","conductivity":""},
{"code":"2573","theta":"","conductivity":""},
{"code":"2574","theta":"","conductivity":""},
{"code":"2580","theta":"","conductivity":""},
{"code":"2581","theta":"","conductivity":""},
{"code":"2582","theta":"","conductivity":""},
{"code":"2583","theta":"","conductivity":""},
{"code":"2584","theta":"","conductivity":""},
{"code":"2590","theta":"","conductivity":""},
{"code":"2591","theta":"","conductivity":""},
{"code":"2592","theta":"","conductivity":""},
{"code":"2593","theta":"","conductivity":""},
{"code":"2600","theta":"","conductivity":""},
{"code":"2601","theta":"","conductivity":""},
{"code":"2602","theta":"","conductivity":""},
{"code":"2603","theta":"","conductivity":""},
{"code":"2604","theta":"","conductivity":""},
{"code":"2605","theta":"","conductivity":""},
{"code":"2610","theta":"","conductivity":""},
{"code":"2611","theta":"","conductivity":""},
{"code":"2612","theta":"","conductivity":""},
{"code":"2613","theta":"","conductivity":""},
{"code":"2614","theta":"","conductivity":""},
{"code":"2620","theta":"","conductivity":""},
{"code":"2621","theta":"","conductivity":""},
{"code":"2622","theta":"","conductivity":""},
{"code":"2630","theta":"","conductivity":""},
{"code":"2631","theta":"","conductivity":""},
{"code":"2640","theta":"","conductivity":""},
{"code":"2641","theta":"","conductivity":""},
{"code":"2642","theta":"","conductivity":""},
{"code":"2650","theta":"","conductivity":""},
{"code":"2651","theta":"","conductivity":""},
{"code":"2652","theta":"","conductivity":""},
{"code":"2653","theta":"","conductivity":""},
{"code":"2660","theta":"","conductivity":""},
{"code":"2661","theta":"","conductivity":""},
{"code":"2670","theta":"","conductivity":""},
{"code":"2671","theta":"","conductivity":""},
{"code":"2672","theta":"","conductivity":""},
{"code":"2680","theta":"","conductivity":""},
{"code":"2681","theta":"","conductivity":""},
{"code":"2682","theta":"","conductivity":""},
{"code":"2683","theta":"","conductivity":""},
{"code":"2690","theta":"","conductivity":""},
{"code":"2691","theta":"","conductivity":""},
{"code":"2700","theta":"","conductivity":""},
{"code":"2701","theta":"","conductivity":""},
{"code":"2710","theta":"","conductivity":""},
{"code":"2711","theta":"","conductivity":""},
{"code":"2712","theta":"","conductivity":""},
{"code":"2713","theta":"","conductivity":""},
{"code":"2720","theta":"","conductivity":""},
{"code":"2721","theta":"","conductivity":""},
{"code":"2722","theta":"","conductivity":""},
{"code":"2723","theta":"","conductivity":""},
{"code":"2730","theta":"","conductivity":""},
{"code":"2731","theta":"","conductivity":""},
{"code":"2732","theta":"","conductivity":""},
{"code":"2740","theta":"","conductivity":""},
{"code":"2741","theta":"","conductivity":""},
{"code":"2742","theta":"","conductivity":""},
{"code":"2743","theta":"","conductivity":""},
{"code":"2750","theta":"","conductivity":""},
{"code":"2751","theta":"","conductivity":""},
{"code":"2752","theta":"","conductivity":""},
{"code":"2753","theta":"","conductivity":""},
{"code":"2760","theta":"","conductivity":""},
{"code":"2761","theta":"","conductivity":""},
{"code":"2762","theta":"","conductivity":""},
{"code":"2763","theta":"","conductivity":""},
{"code":"2764","theta":"","conductivity":""},
{"code":"2765","theta":"","conductivity":""},
{"code":"3000","theta":"","conductivity":""},
{"code":"3010","theta":"","conductivity":""},
{"code":"3020","theta":"","conductivity":""},
{"code":"3030","theta":"","conductivity":""},
{"code":"3031","theta":"","conductivity":""},
{"code":"3032","theta":"","conductivity":""},
{"code":"3033","theta":"","conductivity":""},
{"code":"3050","theta":"","conductivity":""},
{"code":"3060","theta":"0.198","conductivity":"114.9"},
{"code":"3060","theta":"0.205","conductivity":"191.8"},
{"code":"3060","theta":"0.215","conductivity":"241.1"},
{"code":"3060","theta":"0.24","conductivity":"293.8"},
{"code":"3060","theta":"0.26","conductivity":"368.1"},
{"code":"3060","theta":"0.275","conductivity":"442.4"},
{"code":"3060","theta":"0.29","conductivity":"634.2"},
{"code":"3060","theta":"0.3","conductivity":"550.4"},
{"code":"3060","theta":"0.31","conductivity":"864"},
{"code":"3060","theta":"0.32","conductivity":"967.7"},
{"code":"3060","theta":"0.325","conductivity":"1037"},
{"code":"3060","theta":"0.33","conductivity":"1322"},
{"code":"3060","theta":"0.34","conductivity":"1400"},
{"code":"3060","theta":"0.345","conductivity":"1287"},
{"code":"3060","theta":"0.355","conductivity":"1564"},
{"code":"3060","theta":"0.36","conductivity":"1443"},
{"code":"3060","theta":"0.365","conductivity":"1806"},
{"code":"3070","theta":"","conductivity":""},
{"code":"3080","theta":"","conductivity":""},
{"code":"3090","theta":"","conductivity":""},
{"code":"3091","theta":"","conductivity":""},
{"code":"3093","theta":"","conductivity":""},
{"code":"3100","theta":"","conductivity":""},
{"code":"3101","theta":"","conductivity":""},
{"code":"3102","theta":"","conductivity":""},
{"code":"3103","theta":"","conductivity":""},
{"code":"3110","theta":"","conductivity":""},
{"code":"3111","theta":"","conductivity":""},
{"code":"3112","theta":"","conductivity":""},
{"code":"3113","theta":"","conductivity":""},
{"code":"3120","theta":"","conductivity":""},
{"code":"3130","theta":"","conductivity":""},
{"code":"3131","theta":"","conductivity":""},
{"code":"3132","theta":"","conductivity":""},
{"code":"3133","theta":"","conductivity":""},
{"code":"3134","theta":"","conductivity":""},
{"code":"3140","theta":"","conductivity":""},
{"code":"3141","theta":"","conductivity":""},
{"code":"3142","theta":"","conductivity":""},
{"code":"3143","theta":"","conductivity":""},
{"code":"3144","theta":"","conductivity":""},
{"code":"3150","theta":"","conductivity":""},
{"code":"3151","theta":"","conductivity":""},
{"code":"3152","theta":"","conductivity":""},
{"code":"3153","theta":"","conductivity":""},
{"code":"3154","theta":"","conductivity":""},
{"code":"3155","theta":"","conductivity":""},
{"code":"3160","theta":"","conductivity":""},
{"code":"3161","theta":"","conductivity":""},
{"code":"3162","theta":"","conductivity":""},
{"code":"3163","theta":"","conductivity":""},
{"code":"3164","theta":"","conductivity":""},
{"code":"3165","theta":"","conductivity":""},
{"code":"3170","theta":"","conductivity":""},
{"code":"3171","theta":"","conductivity":""},
{"code":"3172","theta":"","conductivity":""},
{"code":"3173","theta":"","conductivity":""},
{"code":"3174","theta":"","conductivity":""},
{"code":"3175","theta":"","conductivity":""},
{"code":"3180","theta":"","conductivity":""},
{"code":"3181","theta":"","conductivity":""},
{"code":"3182","theta":"","conductivity":""},
{"code":"3183","theta":"","conductivity":""},
{"code":"3190","theta":"","conductivity":""},
{"code":"3191","theta":"","conductivity":""},
{"code":"3192","theta":"","conductivity":""},
{"code":"3193","theta":"","conductivity":""},
{"code":"3194","theta":"","conductivity":""},
{"code":"3195","theta":"","conductivity":""},
{"code":"3200","theta":"","conductivity":""},
{"code":"3201","theta":"","conductivity":""},
{"code":"3202","theta":"","conductivity":""},
{"code":"3203","theta":"","conductivity":""},
{"code":"3204","theta":"","conductivity":""},
{"code":"3205","theta":"","conductivity":""},
{"code":"3206","theta":"","conductivity":""},
{"code":"3210","theta":"","conductivity":""},
{"code":"3211","theta":"","conductivity":""},
{"code":"3212","theta":"","conductivity":""},
{"code":"3213","theta":"","conductivity":""},
{"code":"3214","theta":"","conductivity":""},
{"code":"3220","theta":"","conductivity":""},
{"code":"3221","theta":"","conductivity":""},
{"code":"3222","theta":"","conductivity":""},
{"code":"3223","theta":"","conductivity":""},
{"code":"3224","theta":"","conductivity":""},
{"code":"3225","theta":"","conductivity":""},
{"code":"3230","theta":"","conductivity":""},
{"code":"3231","theta":"","conductivity":""},
{"code":"3232","theta":"","conductivity":""},
{"code":"3240","theta":"","conductivity":""},
{"code":"3241","theta":"","conductivity":""},
{"code":"3242","theta":"","conductivity":""},
{"code":"3243","theta":"","conductivity":""},
{"code":"3250","theta":"","conductivity":""},
{"code":"3251","theta":"","conductivity":""},
{"code":"3252","theta":"","conductivity":""},
{"code":"3253","theta":"","conductivity":""},
{"code":"3260","theta":"","conductivity":""},
{"code":"3261","theta":"","conductivity":""},
{"code":"3262","theta":"","conductivity":""},
{"code":"3263","theta":"","conductivity":""},
{"code":"3264","theta":"","conductivity":""},
{"code":"3270","theta":"","conductivity":""},
{"code":"3271","theta":"","conductivity":""},
{"code":"3272","theta":"","conductivity":""},
{"code":"3273","theta":"","conductivity":""},
{"code":"3274","theta":"","conductivity":""},
{"code":"3281","theta":"","conductivity":""},
{"code":"3282","theta":"","conductivity":""},
{"code":"3283","theta":"","conductivity":""},
{"code":"3290","theta":"","conductivity":""},
{"code":"3291","theta":"","conductivity":""},
{"code":"3292","theta":"","conductivity":""},
{"code":"3293","theta":"","conductivity":""},
{"code":"3300","theta":"","conductivity":""},
{"code":"3301","theta":"","conductivity":""},
{"code":"3302","theta":"","conductivity":""},
{"code":"3303","theta":"","conductivity":""},
{"code":"3310","theta":"","conductivity":""},
{"code":"3311","theta":"","conductivity":""},
{"code":"3312","theta":"","conductivity":""},
{"code":"3313","theta":"","conductivity":""},
{"code":"3320","theta":"","conductivity":""},
{"code":"3321","theta":"","conductivity":""},
{"code":"3322","theta":"","conductivity":""},
{"code":"3323","theta":"","conductivity":""},
{"code":"3330","theta":"","conductivity":""},
{"code":"3331","theta":"","conductivity":""},
{"code":"3332","theta":"","conductivity":""},
{"code":"3340","theta":"","conductivity":""},
{"code":"3341","theta":"","conductivity":""},
{"code":"3350","theta":"","conductivity":""},
{"code":"3351","theta":"","conductivity":""},
{"code":"3360","theta":"","conductivity":""},
{"code":"3361","theta":"","conductivity":""},
{"code":"3370","theta":"","conductivity":""},
{"code":"3371","theta":"","conductivity":""},
{"code":"3380","theta":"","conductivity":""},
{"code":"3381","theta":"","conductivity":""},
{"code":"3390","theta":"","conductivity":""},
{"code":"3391","theta":"","conductivity":""},
{"code":"3392","theta":"","conductivity":""},
{"code":"3393","theta":"","conductivity":""},
{"code":"3395","theta":"","conductivity":""},
{"code":"4000","theta":"","conductivity":""},
{"code":"4001","theta":"","conductivity":""},
{"code":"4010","theta":"","conductivity":""},
{"code":"4011","theta":"","conductivity":""},
{"code":"4020","theta":"","conductivity":""},
{"code":"4021","theta":"","conductivity":""},
{"code":"4030","theta":"","conductivity":""},
{"code":"4031","theta":"","conductivity":""},
{"code":"4032","theta":"","conductivity":""},
{"code":"4033","theta":"","conductivity":""},
{"code":"4040","theta":"","conductivity":""},
{"code":"4041","theta":"","conductivity":""},
{"code":"4042","theta":"","conductivity":""},
{"code":"4043","theta":"","conductivity":""},
{"code":"4050","theta":"","conductivity":""},
{"code":"4051","theta":"","conductivity":""},
{"code":"4052","theta":"","conductivity":""},
{"code":"4060","theta":"","conductivity":""},
{"code":"4061","theta":"","conductivity":""},
{"code":"4062","theta":"","conductivity":""},
{"code":"4070","theta":"","conductivity":""},
{"code":"4071","theta":"","conductivity":""},
{"code":"4080","theta":"","conductivity":""},
{"code":"4081","theta":"","conductivity":""},
{"code":"4082","theta":"","conductivity":""},
{"code":"4090","theta":"","conductivity":""},
{"code":"4091","theta":"","conductivity":""},
{"code":"4092","theta":"","conductivity":""},
{"code":"4100","theta":"","conductivity":""},
{"code":"4101","theta":"","conductivity":""},
{"code":"4102","theta":"","conductivity":""},
{"code":"4110","theta":"","conductivity":""},
{"code":"4111","theta":"","conductivity":""},
{"code":"4112","theta":"","conductivity":""},
{"code":"4120","theta":"","conductivity":""},
{"code":"4121","theta":"","conductivity":""},
{"code":"4130","theta":"","conductivity":""},
{"code":"4131","theta":"","conductivity":""},
{"code":"4132","theta":"","conductivity":""},
{"code":"4140","theta":"","conductivity":""},
{"code":"4141","theta":"","conductivity":""},
{"code":"4142","theta":"","conductivity":""},
{"code":"4150","theta":"","conductivity":""},
{"code":"4151","theta":"","conductivity":""},
{"code":"4152","theta":"","conductivity":""},
{"code":"4160","theta":"","conductivity":""},
{"code":"4161","theta":"","conductivity":""},
{"code":"4162","theta":"","conductivity":""},
{"code":"4170","theta":"","conductivity":""},
{"code":"4171","theta":"","conductivity":""},
{"code":"4172","theta":"","conductivity":""},
{"code":"4180","theta":"","conductivity":""},
{"code":"4181","theta":"","conductivity":""},
{"code":"4182","theta":"","conductivity":""},
{"code":"4183","theta":"","conductivity":""},
{"code":"4190","theta":"","conductivity":""},
{"code":"4191","theta":"","conductivity":""},
{"code":"4192","theta":"","conductivity":""},
{"code":"4193","theta":"","conductivity":""},
{"code":"4194","theta":"","conductivity":""},
{"code":"4195","theta":"","conductivity":""},
{"code":"4200","theta":"","conductivity":""},
{"code":"4201","theta":"","conductivity":""},
{"code":"4202","theta":"","conductivity":""},
{"code":"4203","theta":"","conductivity":""},
{"code":"4204","theta":"","conductivity":""},
{"code":"4210","theta":"","conductivity":""},
{"code":"4211","theta":"","conductivity":""},
{"code":"4212","theta":"","conductivity":""},
{"code":"4213","theta":"","conductivity":""},
{"code":"4220","theta":"","conductivity":""},
{"code":"4221","theta":"","conductivity":""},
{"code":"4222","theta":"","conductivity":""},
{"code":"4223","theta":"","conductivity":""},
{"code":"4224","theta":"","conductivity":""},
{"code":"4230","theta":"","conductivity":""},
{"code":"4231","theta":"","conductivity":""},
{"code":"4232","theta":"","conductivity":""},
{"code":"4233","theta":"","conductivity":""},
{"code":"4234","theta":"","conductivity":""},
{"code":"4241","theta":"","conductivity":""},
{"code":"4242","theta":"","conductivity":""},
{"code":"4243","theta":"","conductivity":""},
{"code":"4251","theta":"","conductivity":""},
{"code":"4252","theta":"","conductivity":""},
{"code":"4253","theta":"","conductivity":""},
{"code":"4261","theta":"","conductivity":""},
{"code":"4262","theta":"","conductivity":""},
{"code":"4263","theta":"","conductivity":""},
{"code":"4271","theta":"","conductivity":""},
{"code":"4272","theta":"","conductivity":""},
{"code":"4273","theta":"","conductivity":""},
{"code":"4281","theta":"","conductivity":""},
{"code":"4282","theta":"","conductivity":""},
{"code":"4283","theta":"","conductivity":""},
{"code":"4284","theta":"","conductivity":""},
{"code":"4291","theta":"","conductivity":""},
{"code":"4310","theta":"","conductivity":""},
{"code":"4311","theta":"","conductivity":""},
{"code":"4340","theta":"","conductivity":""},
{"code":"4341","theta":"","conductivity":""},
{"code":"4390","theta":"","conductivity":""},
{"code":"4391","theta":"","conductivity":""},
{"code":"4410","theta":"","conductivity":""},
{"code":"4411","theta":"","conductivity":""},
{"code":"4412","theta":"","conductivity":""},
{"code":"4440","theta":"","conductivity":""},
{"code":"4441","theta":"","conductivity":""},
{"code":"4442","theta":"","conductivity":""},
{"code":"4443","theta":"","conductivity":""},
{"code":"4444","theta":"","conductivity":""},
{"code":"4445","theta":"","conductivity":""},
{"code":"4450","theta":"","conductivity":""},
{"code":"4460","theta":"","conductivity":""},
{"code":"4470","theta":"","conductivity":""},
{"code":"4480","theta":"","conductivity":""},
{"code":"4490","theta":"","conductivity":""},
{"code":"4500","theta":"","conductivity":""},
{"code":"4510","theta":"","conductivity":""},
{"code":"4511","theta":"","conductivity":""},
{"code":"4512","theta":"","conductivity":""},
{"code":"4514","theta":"","conductivity":""},
{"code":"4520","theta":"","conductivity":""},
{"code":"4521","theta":"","conductivity":""},
{"code":"4522","theta":"","conductivity":""},
{"code":"4523","theta":"","conductivity":""},
{"code":"4530","theta":"","conductivity":""},
{"code":"4531","theta":"","conductivity":""},
{"code":"4532","theta":"","conductivity":""},
{"code":"4533","theta":"","conductivity":""},
{"code":"4540","theta":"","conductivity":""},
{"code":"4541","theta":"","conductivity":""},
{"code":"4542","theta":"","conductivity":""},
{"code":"4543","theta":"","conductivity":""},
{"code":"4544","theta":"","conductivity":""},
{"code":"4550","theta":"","conductivity":""},
{"code":"4551","theta":"","conductivity":""},
{"code":"4552","theta":"","conductivity":""},
{"code":"4553","theta":"","conductivity":""},
{"code":"4560","theta":"","conductivity":""},
{"code":"4561","theta":"","conductivity":""},
{"code":"4562","theta":"","conductivity":""},
{"code":"4564","theta":"","conductivity":""},
{"code":"4570","theta":"","conductivity":""},
{"code":"4571","theta":"","conductivity":""},
{"code":"4572","theta":"","conductivity":""},
{"code":"4573","theta":"","conductivity":""},
{"code":"4574","theta":"","conductivity":""},
{"code":"4575","theta":"","conductivity":""},
{"code":"4580","theta":"","conductivity":""},
{"code":"4581","theta":"","conductivity":""},
{"code":"4582","theta":"","conductivity":""},
{"code":"4583","theta":"","conductivity":""},
{"code":"4590","theta":"","conductivity":""},
{"code":"4591","theta":"","conductivity":""},
{"code":"4592","theta":"","conductivity":""},
{"code":"4600","theta":"","conductivity":""},
{"code":"4601","theta":"","conductivity":""},
{"code":"4602","theta":"","conductivity":""},
{"code":"4610","theta":"","conductivity":""},
{"code":"4611","theta":"","conductivity":""},
{"code":"4612","theta":"","conductivity":""},
{"code":"4620","theta":"","conductivity":""},
{"code":"4621","theta":"","conductivity":""},
{"code":"4622","theta":"","conductivity":""},
{"code":"4650","theta":"","conductivity":""},
{"code":"4651","theta":"","conductivity":""},
{"code":"4660","theta":"","conductivity":""},
{"code":"4661","theta":"","conductivity":""},
{"code":"4670","theta":"","conductivity":""},
{"code":"4671","theta":"","conductivity":""},
{"code":"4672","theta":"","conductivity":""},
{"code":"4673","theta":"","conductivity":""},
{"code":"4680","theta":"","conductivity":""},
{"code":"4681","theta":"","conductivity":""},
{"code":"4690","theta":"","conductivity":""},
{"code":"4700","theta":"","conductivity":""},
{"code":"4710","theta":"","conductivity":""},
{"code":"4720","theta":"","conductivity":""},
{"code":"4750","theta":"","conductivity":""},
{"code":"4760","theta":"","conductivity":""},
{"code":"4770","theta":"","conductivity":""},
{"code":"4780","theta":"","conductivity":""},
{"code":"4790","theta":"","conductivity":""},
{"code":"4791","theta":"","conductivity":""},
{"code":"4800","theta":"","conductivity":""},
{"code":"4801","theta":"","conductivity":""},
{"code":"4810","theta":"","conductivity":""},
{"code":"4870","theta":"","conductivity":""},
{"code":"4880","theta":"","conductivity":""},
{"code":"4881","theta":"","conductivity":""},
{"code":"4890","theta":"0.047","conductivity":"1.44"},
{"code":"4890","theta":"0.077","conductivity":"1.44"},
{"code":"4890","theta":"0.103","conductivity":"2.88"},
{"code":"4890","theta":"0.128","conductivity":"4.32"},
{"code":"4890","theta":"0.163","conductivity":"8.64"},
{"code":"4890","theta":"0.19","conductivity":"17.28"},
{"code":"4890","theta":"0.21","conductivity":"20.16"},
{"code":"4890","theta":"0.224","conductivity":"24.48"},
{"code":"4890","theta":"0.24","conductivity":"28.8"},
{"code":"4890","theta":"0.257","conductivity":"31.68"},
{"code":"4890","theta":"0.295","conductivity":"33.12"},
{"code":"4910","theta":"0.278","conductivity":"0.04925"},
{"code":"4910","theta":"0.367","conductivity":"1.065"},
{"code":"4910","theta":"0.433","conductivity":"5.589"},
{"code":"4920","theta":"0.347","conductivity":"0.004"},
{"code":"4920","theta":"0.359","conductivity":"0.0075"},
{"code":"4920","theta":"0.378","conductivity":"0.0101"},
{"code":"4920","theta":"0.394","conductivity":"0.0936"},
{"code":"4920","theta":"0.463","conductivity":"0.1019"},
{"code":"4920","theta":"0.432","conductivity":"0.1808"},
{"code":"4921","theta":"0.448","conductivity":"0.2292"},
{"code":"4921","theta":"0.436","conductivity":"0.3683"},
{"code":"4921","theta":"0.471","conductivity":"0.5797"},
{"code":"4921","theta":"0.519","conductivity":"1.597"},
{"code":"4921","theta":"0.538","conductivity":"3.575"},
{"code":"4921","theta":"0.546","conductivity":"8.303"},
{"code":"4922","theta":"0.271","conductivity":"0.0044"},
{"code":"4922","theta":"0.29","conductivity":"0.0137"},
{"code":"4922","theta":"0.317","conductivity":"0.0549"},
{"code":"4922","theta":"0.342","conductivity":"0.1532"},
{"code":"4923","theta":"0.229","conductivity":"0.00667"},
{"code":"4923","theta":"0.247","conductivity":"0.02406"},
{"code":"4923","theta":"0.272","conductivity":"0.06858"},
{"code":"4923","theta":"0.293","conductivity":"0.2057"},
{"code":"4923","theta":"0.32","conductivity":"0.3743"},
{"code":"4940","theta":"0.116","conductivity":"66.38"},
{"code":"4940","theta":"0.13","conductivity":"107.2"},
{"code":"4940","theta":"0.155","conductivity":"199.2"},
{"code":"4940","theta":"0.18","conductivity":"314"},
{"code":"4940","theta":"0.206","conductivity":"487.7"},
{"code":"4940","theta":"0.219","conductivity":"625.5"},
{"code":"4940","theta":"0.231","conductivity":"755.7"},
{"code":"4940","theta":"0.248","conductivity":"993.2"},
{"code":"4940","theta":"0.254","conductivity":"1162"},
{"code":"4941","theta":"0.008","conductivity":"39.36"},
{"code":"4941","theta":"0.016","conductivity":"53.33"},
{"code":"4941","theta":"0.027","conductivity":"71.11"},
{"code":"4941","theta":"0.041","conductivity":"91.44"},
{"code":"4941","theta":"0.057","conductivity":"121.9"},
{"code":"4941","theta":"0.072","conductivity":"160"},
{"code":"4941","theta":"0.09","conductivity":"205.7"},
{"code":"4941","theta":"0.104","conductivity":"241.3"},
{"code":"4941","theta":"0.115","conductivity":"276.8"},
{"code":"4941","theta":"0.123","conductivity":"307.3"},
{"code":"4941","theta":"0.135","conductivity":"347.9"},
{"code":"4941","theta":"0.147","conductivity":"398.7"},
{"code":"4941","theta":"0.158","conductivity":"439.4"},
{"code":"4941","theta":"0.17","conductivity":"500.3"},
{"code":"4941","theta":"0.181","conductivity":"556.2"},
{"code":"4941","theta":"0.188","conductivity":"603.2"},
{"code":"4941","theta":"0.196","conductivity":"650.2"},
{"code":"4941","theta":"0.201","conductivity":"687"},
{"code":"4941","theta":"0.207","conductivity":"728.9"},
{"code":"4941","theta":"0.214","conductivity":"772.1"},
{"code":"4941","theta":"0.223","conductivity":"827.9"},
{"code":"4941","theta":"0.227","conductivity":"868.6"},
{"code":"4941","theta":"0.232","conductivity":"921.9"},
{"code":"4941","theta":"0.24","conductivity":"975.2"},
{"code":"4950","theta":"0.251","conductivity":"191.5"},
{"code":"4950","theta":"0.282","conductivity":"573.1"},
{"code":"4950","theta":"0.302","conductivity":"990.7"},
{"code":"4950","theta":"0.321","conductivity":"1685"},
{"code":"4950","theta":"0.343","conductivity":"2501"},
{"code":"4950","theta":"0.362","conductivity":"3335"},
{"code":"4950","theta":"0.382","conductivity":"4707"},
{"code":"4960","theta":"","conductivity":""}]
